latexsymb/__init__.py
latexsymb/common.py
latexsymb/core.py
latexsymb/delimiters.py
latexsymb/environments.py
latexsymb/mathematical.py
latexsymb/operators.py
latexsymb-1.0.0.dist-info/METADATA
latexsymb-1.0.0.dist-info/WHEEL
latexsymb-1.0.0.dist-info/top_level.txt
latexsymb-1.0.0.dist-info/RECORD
