Metadata-Version: 2.4
Name: latexsymb
Version: 1.0.0
Summary: A Python package for composable LaTeX mathematical expressions
Author-email: Nicolas Escobar <nescoba@iu.edu>
License: MIT
Project-URL: Homepage, https://nicoesve.github.io/latexsymb-python
Project-URL: Repository, https://github.com/nicoesve/latexsymb-python
Project-URL: Issues, https://github.com/nicoesve/latexsymb-python/issues
Keywords: latex,mathematics,typesetting,symbols
Classifier: Development Status :: 4 - Beta
Classifier: Intended Audience :: Science/Research
Classifier: License :: OSI Approved :: MIT License
Classifier: Programming Language :: Python :: 3
Classifier: Programming Language :: Python :: 3.8
Classifier: Programming Language :: Python :: 3.9
Classifier: Programming Language :: Python :: 3.10
Classifier: Programming Language :: Python :: 3.11
Classifier: Topic :: Scientific/Engineering :: Mathematics
Classifier: Topic :: Text Processing :: Markup :: LaTeX
Requires-Python: >=3.8
Provides-Extra: dev
Requires-Dist: pytest>=7.0; extra == "dev"
Requires-Dist: pytest-cov; extra == "dev"
Requires-Dist: black; extra == "dev"
Requires-Dist: flake8; extra == "dev"
Requires-Dist: mypy; extra == "dev"
